{
  ".": "Руководства разработчика",
  "AI_SIDEBAR_CHAT.md": "Руководство по контекстному ИИ-чату в левой панели, PageContextEnvelope и настройкам chat_settings",
  "AI_SKILLS_OPERATIONS.md": "Операционное руководство по module/runtime AI skills, ai.skill_creator и MCP resources",
  "CHANGE_PATTERNS.md": "Паттерны внесения изменений",
  "INTERFACE_RUSSIFICATION.md": "Правила русскоязычных UI-строк до внедрения полноценной локализации",
  "KNOWLEDGE_ANALYTICS_OPERATIONS.md": "Операционный guide по knowledge-driven business analytics, IMAP, DMS и дедупликации",
  "MEMORY_EXTERNAL_SYSTEMS_QUESTIONNAIRES.md": "Опросники для подключения внешних информационных систем и первичного описания сущностей графа знаний",
  "MEMORY_INGESTION_OPERATIONS.md": "Операционный guide по ingestion документов, review queues и bootstrapping схемы графа памяти",
  "MEMORY_USER_GUIDE.md": "Руководство пользователя и администратора по системе памяти",
  "SETTINGS_CENTER_OPERATIONS.md": "Операционный guide по Settings Center, runtime contracts, users, AD link, ACL и .env proposals",
  "TESTING_POLICY.md": "Политика тестирования, матрица обязательных проверок и независимая проверка субагентом",
  "WORKER_AND_QUEUE_OPERATIONS.md": "Операционный guide по worker-командам, очередям, retry, idempotency и наблюдаемости",
  "PROJECT_REVIEW.md": "Чек-лист ревью проекта",
  "PROJECT_STRUCTURE_SYSTEM.md": "Система автоматического сбора структуры (.desc.json → PROJECT_STRUCTURE.yaml)"
}
